<?xml version="1.0" encoding="UTF-8"?>
<signos>
    <signo>
        <dataInicio>21/03</dataInicio>
        <dataFim>20/04</dataFim>
        <signoNome>Áries</signoNome>
        <descricao>Determinado e enérgico, 
            busca liderar e conquistar desafios.</descricao>
    </signo>
    <signo>
        <dataInicio>21/04</dataInicio>
        <dataFim>20/05</dataFim>
        <signoNome>Touro</signoNome>
        <descricao>Prático e confiável, 
            valoriza a segurança e o conforto.</descricao>
    </signo>
    <signo>
        <dataInicio>21/05</dataInicio>
        <dataFim>20/06</dataFim>
        <signoNome>Gêmeos</signoNome>
        <descricao>Curioso e comunicativo, 
            adora aprender e trocar ideias.</descricao>
    </signo>
    <signo>
        <dataInicio>21/06</dataInicio>
        <dataFim>22/07</dataFim>
        <signoNome>Câncer</signoNome>
        <descricao>Emocional e protetor, 
            valoriza laços familiares e amizades.</descricao>
    </signo>
    <signo>
        <dataInicio>23/07</dataInicio>
        <dataFim>22/08</dataFim>
        <signoNome>Leão</signoNome>
        <descricao>Confiante e carismático, 
            adora ser o centro das atenções.</descricao>
    </signo>
    <signo>
        <dataInicio>23/08</dataInicio>
        <dataFim>22/09</dataFim>
        <signoNome>Virgem</signoNome>
        <descricao>Detalhista e organizado, 
            gosta de ajudar e solucionar problemas.</descricao>
    </signo>
    <signo>
        <dataInicio>23/09</dataInicio>
        <dataFim>22/10</dataFim>
        <signoNome>Libra</signoNome>
        <descricao>Diplomático e justo, 
            busca harmonia em todas as áreas da vida.</descricao>
    </signo>
    <signo>
        <dataInicio>23/10</dataInicio>
        <dataFim>21/11</dataFim>
        <signoNome>Escorpião</signoNome>
        <descricao>Intenso e apaixonado, 
            possui grande força emocional.</descricao>
    </signo>
    <signo>
        <dataInicio>22/11</dataInicio>
        <dataFim>21/12</dataFim>
        <signoNome>Sagitário</signoNome>
        <descricao>Aventureiro e otimista, 
            busca novas experiências e liberdade.</descricao>
    </signo>
    <signo>
        <dataInicio>22/12</dataInicio>
        <dataFim>20/01</dataFim>
        <signoNome>Capricórnio</signoNome>
        <descricao>Disciplinado e ambicioso, 
            trabalha duro para alcançar seus objetivos.</descricao>
    </signo>
    <signo>
        <dataInicio>21/01</dataInicio>
        <dataFim>19/02</dataFim>
        <signoNome>Aquário</signoNome>
        <descricao>Inovador e independente, 
            valoriza a liberdade e novas ideias.</descricao>
    </signo>
    <signo>
        <dataInicio>20/02</dataInicio>
        <dataFim>20/03</dataFim>
        <signoNome>Peixes</signoNome>
        <descricao>Sensível e intuitivo, 
            possui grande imaginação e empatia.</descricao>
    </signo>
</signos>
